es_stats/__init__.py
es_stats/classes.py
es_stats/exceptions.py
es_stats/utils.py
es_stats/version.py
es_stats-1.2.0.dist-info/METADATA
es_stats-1.2.0.dist-info/RECORD
es_stats-1.2.0.dist-info/WHEEL
es_stats-1.2.0.dist-info/top_level.txt
