Metadata-Version: 2.1
Name: es-stats
Version: 1.2.0
Summary: "Collect metrics from Elasticsearch"
Home-page: http://github.com/untergeek/es_stats
Author: Aaron Mildenstein
Author-email: aaron@mildensteins.com
License: Apache License, Version 2.0
Keywords: elasticsearch,stats
Platform: UNKNOWN
Classifier: Intended Audience :: Developers
Classifier: Intended Audience :: System Administrators
Classifier: License :: OSI Approved :: Apache Software License
Classifier: Operating System :: OS Independent
Classifier: Programming Language :: Python :: 2.7
Classifier: Programming Language :: Python :: 3.5
Classifier: Programming Language :: Python :: 3.6
Requires-Dist: setuptools (>=30.3.0)
Requires-Dist: dotmap (>=1.2.20)
Requires-Dist: elasticsearch (>=5.5.2)
